dome.py
d2_dome-1.0.2.dist-info/LICENSE
d2_dome-1.0.2.dist-info/WHEEL
d2_dome-1.0.2.dist-info/METADATA
d2_dome-1.0.2.dist-info/RECORD
